smurves/__init__.py
smurves/smurves.py
smurves-1.0.1.dist-info/LICENSE.txt
smurves-1.0.1.dist-info/METADATA
smurves-1.0.1.dist-info/WHEEL
smurves-1.0.1.dist-info/top_level.txt
smurves-1.0.1.dist-info/RECORD
