Metadata-Version: 2.1
Name: smurves
Version: 1.0.1
Summary: The triple-random constrainable curve generator for smooth function perturbation
Home-page: https://github.com/moews/smurves
Author: Ben Moews
Author-email: ben.moews@protonmail.com
License: UNKNOWN
Keywords: astronomy,astrophysics,cosmology,randomized algorithms,function perturbation
Platform: UNKNOWN
Classifier: Programming Language :: Python :: 3 :: Only
Classifier: Intended Audience :: Science/Research
Classifier: License :: OSI Approved :: MIT License
Requires-Dist: numpy
